Workbook

Sheet Start here
A1: Family budget tracker
A3: This workbook is yours. It stays on your phone or computer until you upload it to the family ledger page.
A5: Setting it up (once)
A6: 1. Pay sheet: type each person's name and monthly take-home pay (after tax) in the yellow cells. Up to four people.
A7: 2. Budget sheet: type the first month you want to track in the yellow cell at the top (for example 1 Oct 2026). The next 12 months fill in by themselves.
A8: 3. Budget sheet: one row per expense. Choose Needs, Wants or Savings, name it, choose who pays it, and type the planned monthly amount.
A9: If you have a loan from the family, add a Needs line called Loan repayment with this month's amount from your statement.
A11: Every month
A12: 4. Budget sheet: type what was actually spent in that month's column.
A13: 5. Summary sheet: choose the month at the top to compare plan and actual spending with the 50/30/20 guide.
A15: Uploading to the family ledger
A16: 6. Save the workbook. Open the family ledger page, go to Budget, and upload it. The file name doesn't matter.
... A22: Example of a Budget row (shown here only, not counted)
A23: Category | B23: Item | C23: Paid by | D23: Planned monthly | E23: Oct 2026 actual
A24: Needs | B24: Groceries | C24: Shared | D24: 5800 | E24: 6150

Sheet Summary
A1: Summary
A3: Month | B3: =Budget!E5 -> Oct 2026 | C3: Choose a month from the list.
A4: Take-home pay | B4: =Pay!B8 -> 0
A6: Category | B6: Planned | C6: Planned % of pay | D6: Actual | E6: Actual % of pay | F6: Guide
A7: Needs | B7: =SUMIFS(Budget!$D$6:$D$65,Budget!$A$6:$A$65,A7) -> 0 | C7: =IF($B$4>0,B7/$B$4,0) -> 0 | D7: =IFERROR(SUMIFS(INDEX(Budget!$E$6:$P$65,0,MATCH($B$3,Budget!$E$5:$P$5,0)),Budget!$A$6:$A$65,A7),0) -> 0 | E7: =IF($B$4>0,D7/$B$4,0) -> 0 | F7: 0.5
A8: Wants | B8: =SUMIFS(Budget!$D$6:$D$65,Budget!$A$6:$A$65,A8) -> 0 | C8: =IF($B$4>0,B8/$B$4,0) -> 0 | D8: =IFERROR(SUMIFS(INDEX(Budget!$E$6:$P$65,0,MATCH($B$3,Budget!$E$5:$P$5,0)),Budget!$A$6:$A$65,A8),0) -> 0 | E8: =IF($B$4>0,D8/$B$4,0) -> 0 | F8: 0.3
A9: Savings | B9: =SUMIFS(Budget!$D$6:$D$65,Budget!$A$6:$A$65,A9) -> 0 | C9: =IF($B$4>0,B9/$B$4,0) -> 0 | D9: =IFERROR(SUMIFS(INDEX(Budget!$E$6:$P$65,0,MATCH($B$3,Budget!$E$5:$P$5,0)),Budget!$A$6:$A$65,A9),0) -> 0 | E9: =IF($B$4>0,D9/$B$4,0) -> 0 | F9: 0.2
A10: Total | B10: =SUM(B7:B9) -> 0 | C10: =IF($B$4>0,B10/$B$4,0) -> 0 | D10: =SUM(D7:D9) -> 0 | E10: =IF($B$4>0,D10/$B$4,0) -> 0
A11: Not yet planned | B11: =B4-B10 -> 0
C12: =IF(SUMPRODUCT((Budget!$A$6:$A$65="")*(Budget!$D$6:$D$65>0))>0,"Some planned amounts have no category and are not counted","")
A14: Who pays
A15: Person | B15: Take-home pay | C15: Planned share | D15: Left over
A16: =IF(Pay!A4="","",Pay!A4) | B16: =IF(A16="","",Pay!B4) | C16: =IF(A16="","",SUMIFS(Budget!$D$6:$D$65,Budget!$C$6:$C$65,A16)+SUMIFS(Budget!$D$6:$D$65,Budget!$C$6:$C$65,"Shared")/MAX(1,COUNTIF(Pay!$A$4:$A$7,"?*"))) | D16: =IF(A16="","",B16-C16)
A17: =IF(Pay!A5="","",Pay!A5) | B17: =IF(A17="","",Pay!B5) | C17: =IF(A17="","",SUMIFS(Budget!$D$6:$D$65,Budget!$C$6:$C$65,A17)+SUMIFS(Budget!$D$6:$D$65,Budget!$C$6:$C$65,"Shared")/MAX(1,COUNTIF(Pay!$A$4:$A$7,"?*"))) | D17: =IF(A17="","",B17-C17)
A18: =IF(Pay!A6="","",Pay!A6) | B18: =IF(A18="","",Pay!B6) | C18: =IF(A18="","",SUMIFS(Budget!$D$6:$D$65,Budget!$C$6:$C$65,A18)+SUMIFS(Budget!$D$6:$D$65,Budget!$C$6:$C$65,"Shared")/MAX(1,COUNTIF(Pay!$A$4:$A$7,"?*"))) | D18: =IF(A18="","",B18-C18)
A19: =IF(Pay!A7="","",Pay!A7) | B19: =IF(A19="","",Pay!B7) | C19: =IF(A19="","",SUMIFS(Budget!$D$6:$D$65,Budget!$C$6:$C$65,A19)+SUMIFS(Budget!$D$6:$D$65,Budget!$C$6:$C$65,"Shared")/MAX(1,COUNTIF(Pay!$A$4:$A$7,"?*"))) | D19: =IF(A19="","",B19-C19)
A21: Shared lines are split equally between everyone named on the Pay sheet. Lines with no "Paid by" are not included.

Sheet Pay
A1: Who is in this budget
A2: Names and monthly take-home pay (after tax). Leave unused rows empty.
A3: Person | B3: Take-home pay
A8: Total | B8: =SUM(B4:B7) -> 0

Sheet Lists
A1: Shared | B1: Needs
A2: =IF(Pay!A4="","",Pay!A4) | B2: Wants
A3: =IF(Pay!A5="","",Pay!A5) | B3: Savings
A4: =IF(Pay!A6="","",Pay!A6)
A5: =IF(Pay!A7="","",Pay!A7)

Sheet Budget
A1: Budget lines
A2: First month | B2: 46296 | C2: Type the first month to track; the month columns follow from it.
A3: Planned monthly amount in column D; what was actually spent each month from column E.
A5: Category | B5: Item | C5: Paid by | D5: Planned monthly | E5: =TEXT(EDATE($B$2,0),"mmm yyyy") -> Oct 2026 | F5: =TEXT(EDATE($B$2,1),"mmm yyyy") -> Nov 2026 | G5: =TEXT(EDATE($B$2,2),"mmm yyyy") -> Dec 2026 | H5: =TEXT(EDATE($B$2,3),"mmm yyyy") -> Jan 2027 | I5: =TEXT(EDATE($B$2,4),"mmm yyyy") -> Feb 2027 | J5: =TEXT(EDATE($B$2,5),"mmm yyyy") -> Mar 2027 | K5: =TEXT(EDATE($B$2,6),"mmm yyyy") -> Apr 2027 | L5: =TEXT(EDATE($B$2,7),"mmm yyyy") -> May 2027 | M5: =TEXT(EDATE($B$2,8),"mmm yyyy") -> Jun 2027 | N5: =TEXT(EDATE($B$2,9),"mmm yyyy") -> Jul 2027 | O5: =TEXT(EDATE($B$2,10),"mmm yyyy") -> Aug 2027 | P5: =TEXT(EDATE($B$2,11),"mmm yyyy") -> Sep 2027
B66: Total | D66: =SUM(D6:D65) -> 0 | E66: =SUM(E6:E65) -> 0 | F66: =SUM(F6:F65) -> 0 | G66: =SUM(G6:G65) -> 0 | H66: =SUM(H6:H65) -> 0 | I66: =SUM(I6:I65) -> 0 | J66: =SUM(J6:J65) -> 0 | K66: =SUM(K6:K65) -> 0 | ... P66: =SUM(P6:P65) -> 0
